{"[PAD]": 0, "[UNK]": 1, "a": 2, "b": 3, "d": 4, "dz": 5, "e": 6, "f": 7, "g": 8, "gb": 9, "h": 10, "i": 11, "k": 12, "kp": 13, "l": 14, "m": 15, "n": 16, "ndz": 17, "o": 18, "p": 19, "s": 20, "t": 21, "u": 22, "v": 23, "w": 24, "y": 25, "z": 26, "|": 27, "\u00e1": 28, "\u00e2": 29, "\u00e9": 30, "\u00ea": 31, "\u00ed": 32, "\u00ee": 33, "\u00f3": 34, "\u00f4": 35, "\u00fa": 36, "\u00fb": 37, "\u0101": 38, "\u0113": 39, "\u011b": 40, "\u012b": 41, "\u0144": 42, "\u014b": 43, "\u014d": 44, "\u016b": 45, "\u01ce": 46, "\u01d0": 47, "\u01d2": 48, "\u01d4": 49, "\u01f9": 50, "\u0254": 51, "\u0254\u0301": 52, "\u0254\u0302": 53, "\u0254\u0304": 54, "\u0254\u030c": 55, "\u0259": 56, "\u0259\u0301": 57, "\u0259\u0302": 58, "\u0259\u0304": 59, "\u0259\u030c": 60, "\u025b": 61, "\u025b\u0301": 62, "\u025b\u0302": 63, "\u025b\u0304": 64, "\u025b\u030c": 65, "\u0300": 66, "\u0301": 67, "\u0302": 68, "\u0304": 69, "\u030c": 70}